MANIFEST.in
README.md
entrypoints.conf
requirements.txt
setup.py
redbike/VERSION
redbike/__init__.py
redbike/cli.py
redbike/schedule.py
redbike.egg-info/PKG-INFO
redbike.egg-info/SOURCES.txt
redbike.egg-info/dependency_links.txt
redbike.egg-info/entry_points.txt
redbike.egg-info/requires.txt
redbike.egg-info/top_level.txt